postgresql_kernel/__init__.py
postgresql_kernel/__main__.py
postgresql_kernel/kernel.json
postgresql_kernel/kernel.py
postgresql_kernel/images/logo-32x32.png
postgresql_kernel/images/logo-512x512.png
postgresql_kernel/images/logo-64x64.png
postgresql_kernel-0.0.2.data/data/share/jupyter/kernels/postgresql/kernel.json
postgresql_kernel-0.0.2.data/data/share/jupyter/kernels/postgresql/logo-32x32.png
postgresql_kernel-0.0.2.data/data/share/jupyter/kernels/postgresql/logo-512x512.png
postgresql_kernel-0.0.2.data/data/share/jupyter/kernels/postgresql/logo-64x64.png
postgresql_kernel-0.0.2.dist-info/LICENSE
postgresql_kernel-0.0.2.dist-info/METADATA
postgresql_kernel-0.0.2.dist-info/WHEEL
postgresql_kernel-0.0.2.dist-info/top_level.txt
postgresql_kernel-0.0.2.dist-info/RECORD
