Metadata-Version: 2.1
Name: postgresql-kernel
Version: 0.0.2
Summary: metakernel for postgres_kernel
Home-page: UNKNOWN
Author: hsz
Author-email: hsz1273327@gmail.com
License: MIT License
Keywords: jupyter,jupyter-kernel,postgresql,sql
Platform: Any
Classifier: License :: OSI Approved :: MIT License
Classifier: Programming Language :: Python :: 3.8
Classifier: Programming Language :: Python :: 3.9
Classifier: Programming Language :: Python :: 3.10
Requires-Python: >=3.8
License-File: LICENSE
Requires-Dist: metakernel (>=0.24.0)
Requires-Dist: psycopg2-binary (>=2.9.3)
Requires-Dist: tabulate (>=0.8.9)
Requires-Dist: jupyter-client (>=7.1.1)
Requires-Dist: ipykernel (>=6.7.0)
